kindle/__init__.py
kindle/model.py
kindle/trainer.py
kindle/version.py
kindle/generator/__init__.py
kindle/generator/add.py
kindle/generator/base_generator.py
kindle/generator/bottleneck.py
kindle/generator/concat.py
kindle/generator/conv.py
kindle/generator/custom_yaml_module.py
kindle/generator/flatten.py
kindle/generator/identity.py
kindle/generator/linear.py
kindle/generator/mobilevit.py
kindle/generator/nn.py
kindle/generator/poolings.py
kindle/generator/pretrained.py
kindle/generator/upsample.py
kindle/generator/yolo_head.py
kindle/modules/__init__.py
kindle/modules/activation.py
kindle/modules/add.py
kindle/modules/bottleneck.py
kindle/modules/concat.py
kindle/modules/conv.py
kindle/modules/dwconv.py
kindle/modules/linear.py
kindle/modules/mobilevit.py
kindle/modules/poolings.py
kindle/modules/pretrained.py
kindle/modules/yolo_head.py
kindle/utils/__init__.py
kindle/utils/model_utils.py
kindle/utils/torch_utils.py
kindle-0.4.16.dist-info/LICENSE
kindle-0.4.16.dist-info/METADATA
kindle-0.4.16.dist-info/WHEEL
kindle-0.4.16.dist-info/top_level.txt
kindle-0.4.16.dist-info/RECORD
