Metadata-Version: 2.1
Name: kindle
Version: 0.4.16
Summary: Kindle - Making a PyTorch model easier than ever!
Home-page: https://github.com/JeiKeiLim/kindle
Author: Jongkuk Lim
Author-email: lim.jeikei@gmail.com
License: MIT License  Copyright (c) 2021 Jongkuk Lim  Permission is hereby granted, free of charge, to any person obtaining a copy of this software and associated documentation files (the "Software"), to deal in the Software without restriction, including without limitation the rights to use, copy, modify, merge, publish, distribute, sublicense, and/or sell copies of the Software, and to permit persons to whom the Software is furnished to do so, subject to the following conditions:  The above co
Platform: UNKNOWN
Classifier: Programming Language :: Python :: 3.6
Classifier: Programming Language :: Python :: 3.7
Classifier: Programming Language :: Python :: 3.8
Requires-Dist: tqdm (>=4.56.0)
Requires-Dist: PyYAML (>=5.3.1)
Requires-Dist: torch (>=1.7.1)
Requires-Dist: ptflops (>=0.6.4)
Requires-Dist: timm (>=0.4.5)
Requires-Dist: tabulate (>=0.8.9)
Requires-Dist: einops (>=0.3.2)
